socketsc/__init__.py
socketsc/client.py
socketsc/constants.py
socketsc/logger.py
socketsc/packet.py
socketsc/server.py
socketsc/utils.py
socketsc/version.py
socketsc-1.9.dist-info/LICENSE
socketsc-1.9.dist-info/METADATA
socketsc-1.9.dist-info/WHEEL
socketsc-1.9.dist-info/top_level.txt
socketsc-1.9.dist-info/RECORD
