Metadata-Version: 2.1
Name: socketsc
Version: 1.9
Summary: Simple socket library for client/server with events management.
Home-page: https://gitlab.com/dan5py/socketsc
Author: Dan5py
License: MIT
Keywords: server client socket event tcp
Classifier: License :: OSI Approved :: MIT License
Classifier: Intended Audience :: Developers
Classifier: Operating System :: OS Independent
Classifier: Programming Language :: Python
Classifier: Programming Language :: Python :: 3
Classifier: Programming Language :: Python :: 3.8
Classifier: Programming Language :: Python :: 3.9
Classifier: Programming Language :: Python :: 3.9
Classifier: Programming Language :: Python :: 3.10
Classifier: Programming Language :: Python :: 3.11
Requires: wheel
Requires-Python: >=3.8.0
License-File: LICENSE
